miniwdl_lsf/__init__.py
miniwdl_lsf-0.2.0.dist-info/LICENSE
miniwdl_lsf-0.2.0.dist-info/METADATA
miniwdl_lsf-0.2.0.dist-info/WHEEL
miniwdl_lsf-0.2.0.dist-info/entry_points.txt
miniwdl_lsf-0.2.0.dist-info/RECORD
