Metadata-Version: 2.1
Name: miniwdl-lsf
Version: 0.2.0
Summary: miniwdl lsf backend using singularity
Home-page: https://github.com/adthrasher/miniwdl-lsf/
License: MIT
Keywords: WDL,miniwdl,workflow language,LSF,Singularity
Author: Andrew Thrasher
Author-email: adthrasher@gmail.com
Requires-Python: >3.6
Classifier: License :: OSI Approved :: MIT License
Classifier: Programming Language :: Python :: 3
Classifier: Programming Language :: Python :: 3.7
Classifier: Programming Language :: Python :: 3.8
Classifier: Programming Language :: Python :: 3.9
Classifier: Programming Language :: Python :: 3.10
Classifier: Programming Language :: Python :: 3.11
Classifier: Topic :: System :: Distributed Computing
Requires-Dist: miniwdl (>=1.7.0)
Project-URL: Documentation, https://adthrasher.github.io/miniwdl-lsf/
Project-URL: Repository, https://github.com/adthrasher/miniwdl-lsf/
